<?xml version="1.0" encoding="UTF-8"?>
<!DOCTYPE suite SYSTEM "https://testng.org/testng-1.0.dtd">
<suite name="Suite">
<listeners>
<listener class-name="FMClient.ActionCaptureListener"></listener>
</listeners>
  <test thread-count="15" name="Test">
    <classes>
      <class name="FMClient.Newtestrulecreation"/>
      <class name="FMClient.Newrulecreation"/>
      <class name="FMClient.Templaterule"/>
      <class name="FMClient.HotlistFromFile"/>
      <class name="FMClient.Hotlist"/>
      <class name="FMClient.StandardNickname"/>
      <class name="FMClient.Customnickname"/>
      <class name="FMClient.ClosedAlarms"/>
      <class name="FMClient.OpenAlarms"/>
      <class name="FMClient.GlobalExceptionPage"/>
      <class name="FMClient.Usertest"/>
      <class name="FMClient.RecordView2Adavncedfilter"/>
      <class name="FMClient.RecordViewCDR"/>
      <class name="FMClient.ActiveAlarms"/>
      <class name="FMClient.Export"/>
    </classes>
  </test> <!-- Test -->
</suite> <!-- Suite -->
